xiaoya_teacher_mcp_server/config.py
xiaoya_teacher_mcp_server/main.py
xiaoya_teacher_mcp_server/tools/__init__.py
xiaoya_teacher_mcp_server/tools/group/__init__.py
xiaoya_teacher_mcp_server/tools/group/query.py
xiaoya_teacher_mcp_server/tools/group/update.py
xiaoya_teacher_mcp_server/tools/questions/__init__.py
xiaoya_teacher_mcp_server/tools/questions/create.py
xiaoya_teacher_mcp_server/tools/questions/delete.py
xiaoya_teacher_mcp_server/tools/questions/query.py
xiaoya_teacher_mcp_server/tools/questions/update.py
xiaoya_teacher_mcp_server/tools/resources/__init__.py
xiaoya_teacher_mcp_server/tools/resources/create.py
xiaoya_teacher_mcp_server/tools/resources/delete.py
xiaoya_teacher_mcp_server/tools/resources/query.py
xiaoya_teacher_mcp_server/tools/resources/update.py
xiaoya_teacher_mcp_server/tools/task/__init__.py
xiaoya_teacher_mcp_server/tools/task/query.py
xiaoya_teacher_mcp_server/types/types.py
xiaoya_teacher_mcp_server/utils/response.py
xiaoya_teacher_mcp_server-1.1.1.dist-info/METADATA
xiaoya_teacher_mcp_server-1.1.1.dist-info/WHEEL
xiaoya_teacher_mcp_server-1.1.1.dist-info/entry_points.txt
xiaoya_teacher_mcp_server-1.1.1.dist-info/licenses/LICENSE
xiaoya_teacher_mcp_server-1.1.1.dist-info/RECORD
