Metadata-Version: 2.4
Name: xiaoya-teacher-mcp-server
Version: 1.1.1
Summary: 小雅教育管理MCP服务器 - 专为教师设计,提供课程资源管理和试题创建工具
Project-URL: Homepage, https://github.com/Sav1ouR520/xiaoya-teacher-mcp-server
Project-URL: Repository, https://github.com/Sav1ouR520/xiaoya-teacher-mcp-server
Author-email: Sav1ouR520 <3300233150@qq.com>
License: MIT
License-File: LICENSE
Requires-Python: >=3.11
Requires-Dist: markitdown[all]>=0.1.3
Requires-Dist: mcp[cli]==1.19.0
Requires-Dist: requests>=2.32.5
